bilby/__init__.py
bilby/_version.py
bilby/bilby_mcmc/__init__.py
bilby/bilby_mcmc/chain.py
bilby/bilby_mcmc/flows.py
bilby/bilby_mcmc/proposals.py
bilby/bilby_mcmc/sampler.py
bilby/bilby_mcmc/utils.py
bilby/core/__init__.py
bilby/core/fisher.py
bilby/core/grid.py
bilby/core/likelihood.py
bilby/core/result.py
bilby/core/series.py
bilby/core/prior/__init__.py
bilby/core/prior/analytical.py
bilby/core/prior/base.py
bilby/core/prior/conditional.py
bilby/core/prior/dict.py
bilby/core/prior/interpolated.py
bilby/core/prior/joint.py
bilby/core/prior/slabspike.py
bilby/core/sampler/__init__.py
bilby/core/sampler/base_sampler.py
bilby/core/sampler/cpnest.py
bilby/core/sampler/dnest4.py
bilby/core/sampler/dynamic_dynesty.py
bilby/core/sampler/dynesty.py
bilby/core/sampler/dynesty3_utils.py
bilby/core/sampler/dynesty_utils.py
bilby/core/sampler/emcee.py
bilby/core/sampler/fake_sampler.py
bilby/core/sampler/kombine.py
bilby/core/sampler/nessai.py
bilby/core/sampler/nestle.py
bilby/core/sampler/polychord.py
bilby/core/sampler/proposal.py
bilby/core/sampler/ptemcee.py
bilby/core/sampler/ptmcmc.py
bilby/core/sampler/pymc.py
bilby/core/sampler/pymultinest.py
bilby/core/sampler/ultranest.py
bilby/core/sampler/zeus.py
bilby/core/utils/__init__.py
bilby/core/utils/calculus.py
bilby/core/utils/cmd.py
bilby/core/utils/colors.py
bilby/core/utils/constants.py
bilby/core/utils/conversion.py
bilby/core/utils/counter.py
bilby/core/utils/docs.py
bilby/core/utils/entry_points.py
bilby/core/utils/env.py
bilby/core/utils/introspection.py
bilby/core/utils/io.py
bilby/core/utils/log.py
bilby/core/utils/meta_data.py
bilby/core/utils/plotting.py
bilby/core/utils/random.py
bilby/core/utils/samples.py
bilby/core/utils/series.py
bilby/gw/__init__.py
bilby/gw/conversion.py
bilby/gw/cosmology.py
bilby/gw/prior.py
bilby/gw/result.py
bilby/gw/source.py
bilby/gw/utils.py
bilby/gw/waveform_generator.py
bilby/gw/detector/__init__.py
bilby/gw/detector/calibration.py
bilby/gw/detector/geometry.py
bilby-2.7.1.dist-info/licenses/AUTHORS.md
bilby-2.7.1.dist-info/licenses/LICENSE.md
bilby-2.7.1.dist-info/METADATA
bilby-2.7.1.dist-info/WHEEL
bilby-2.7.1.dist-info/entry_points.txt
bilby-2.7.1.dist-info/top_level.txt
bilby-2.7.1.dist-info/RECORD
