Metadata-Version: 2.4
Name: bilby
Version: 2.7.1
Summary: A user-friendly Bayesian inference library
Author: Bilby Developers
Maintainer: Greg Ashton, Sylvia Biscoveanu, Colm Talbot, Aditya Vijaykumar, Michael J. Williams
License: MIT License
Project-URL: Documentation, https://bilby.readthedocs.io
Project-URL: Homepage, https://github.com/bilby-dev/bilby
Project-URL: Source, https://github.com/bilby-dev/bilby
Project-URL: Tracker, https://github.com/bilby-dev/bilby/issues
Classifier: Development Status :: 5 - Production/Stable
Classifier: Intended Audience :: Science/Research
Classifier: License :: OSI Approved :: MIT License
Classifier: Programming Language :: Python :: 3
Classifier: Topic :: Scientific/Engineering :: Physics
Requires-Python: >=3.10
License-File: LICENSE.md
License-File: AUTHORS.md
Requires-Dist: bilby.cython>=0.3.0
Requires-Dist: dynesty>=2.0.1
Requires-Dist: emcee
Requires-Dist: corner
Requires-Dist: numpy
Requires-Dist: matplotlib
Requires-Dist: scipy>=1.5
Requires-Dist: pandas
Requires-Dist: dill
Requires-Dist: tqdm
Requires-Dist: h5py
Requires-Dist: attrs
Requires-Dist: importlib-metadata>=3.6; python_version < "3.10"
Provides-Extra: all
Requires-Dist: astropy>=5; extra == "all"
Requires-Dist: lalsuite; extra == "all"
Requires-Dist: gwpy; extra == "all"
Requires-Dist: pyfftw; extra == "all"
Requires-Dist: scikit-learn; extra == "all"
Requires-Dist: scikit-learn; extra == "all"
Requires-Dist: glasflow; extra == "all"
Requires-Dist: cpnest>=0.9.4; extra == "all"
Requires-Dist: dynesty; extra == "all"
Requires-Dist: emcee; extra == "all"
Requires-Dist: nestle; extra == "all"
Requires-Dist: ptmcmcsampler!=0.0.0,!=2.1.0; extra == "all"
Requires-Dist: ptemcee; extra == "all"
Requires-Dist: pymc>=4.0.0; extra == "all"
Requires-Dist: pymultinest; extra == "all"
Requires-Dist: kombine; extra == "all"
Requires-Dist: ultranest>=3.0.0; extra == "all"
Requires-Dist: nessai>=0.7.0; extra == "all"
Requires-Dist: schwimmbad; extra == "all"
Requires-Dist: zeus-mcmc>=2.3.0; extra == "all"
Requires-Dist: celerite; extra == "all"
Requires-Dist: george; extra == "all"
Requires-Dist: plotly; extra == "all"
Requires-Dist: pytest-requires; extra == "all"
Requires-Dist: pytest-rerunfailures; extra == "all"
Provides-Extra: gw
Requires-Dist: astropy>=5; extra == "gw"
Requires-Dist: lalsuite; extra == "gw"
Requires-Dist: gwpy; extra == "gw"
Requires-Dist: pyfftw; extra == "gw"
Requires-Dist: scikit-learn; extra == "gw"
Provides-Extra: mcmc
Requires-Dist: scikit-learn; extra == "mcmc"
Requires-Dist: glasflow; extra == "mcmc"
Dynamic: license-file
